verlpy/RL_helper.py
verlpy/__init__.py
verlpy/cocotb_env.py
verlpy/utils.py
verlpy-0.9.1.dist-info/LICENSE.txt
verlpy-0.9.1.dist-info/METADATA
verlpy-0.9.1.dist-info/WHEEL
verlpy-0.9.1.dist-info/top_level.txt
verlpy-0.9.1.dist-info/RECORD
