Metadata-Version: 2.1
Name: verlpy
Version: 0.9.1
Summary: A library to use Reinforcement Learning (RL) for digital hardware verification
Home-page: https://github.com/aebeljs/VeRLPy
Author: Aebel Joe Shibu
Author-email: aebeljs@gmail.com
License: UNKNOWN
Project-URL: Bug Tracker, https://github.com/aebeljs/VeRLPy/issues
Platform: UNKNOWN
Classifier: Programming Language :: Python :: 3
Classifier: License :: OSI Approved :: MIT License
Classifier: Operating System :: OS Independent
Requires-Python: >=3.6
License-File: LICENSE.txt
Requires-Dist: cocotb
Requires-Dist: gym
Requires-Dist: stable-baselines3
Requires-Dist: matplotlib
